README.md
setup.py
make2help/__init__.py
make2help/make2help.py
make2help.egg-info/PKG-INFO
make2help.egg-info/SOURCES.txt
make2help.egg-info/dependency_links.txt
make2help.egg-info/entry_points.txt
make2help.egg-info/top_level.txt