Metadata-Version: 1.1
Name: make2help
Version: 0.0.1
Summary: Show all target in Makefile
Home-page: https://github.com/515hikaru/make2help
Author: 515hikaru
Author-email: karanodeny@gmail.com
License: UNKNOWN
Platform: UNKNOWN
Classifier: Development Status :: 3 - Alpha
Classifier: Intended Audience :: Developers
Classifier: Topic :: Software Development :: Build Tools
Classifier: License :: OSI Approved :: MIT License
Classifier: Programming Language :: Python :: 3.5
Classifier: Programming Language :: Python :: 3.6
